google_photos_slideshow/__init__.py
google_photos_slideshow/google_photos_slideshow.py
google_photos_slideshow/index.html
google_photos_slideshow-0.1.0.dist-info/LICENSE
google_photos_slideshow-0.1.0.dist-info/METADATA
google_photos_slideshow-0.1.0.dist-info/WHEEL
google_photos_slideshow-0.1.0.dist-info/entry_points.txt
google_photos_slideshow-0.1.0.dist-info/top_level.txt
google_photos_slideshow-0.1.0.dist-info/RECORD
