Metadata-Version: 2.2
Name: google-photos-slideshow
Version: 0.1.0
Summary: A communal live photo slideshow for Google Photos
Author-email: Torin Halsted <modularizer@gmail.com>
License: This is free and unencumbered software released into the public domain.
Project-URL: Homepage, https://github.com/modularizer/google-photos-slideshow
Keywords: google,photos,slideshow,live,photo,frame
Classifier: Programming Language :: Python :: 3
Classifier: Operating System :: OS Independent
Requires-Python: >=3.10
License-File: LICENSE
Requires-Dist: aiohttp
Requires-Dist: websockets
Requires-Dist: PyYAML
